{
  "esm/final-form-bootstrap3.js": {
    "bundled": 29366,
    "minified": 18638,
    "gzipped": 4194,
    "treeshaked": {
      "rollup": {
        "code": 15560,
        "import_statements": 635
      },
      "webpack": {
        "code": 17659
      }
    }
  },
  "umd/final-form-bootstrap3.js": {
    "bundled": 300191,
    "minified": 109622,
    "gzipped": 32958
  },
  "umd/final-form-bootstrap3.min.js": {
    "bundled": 137373,
    "minified": 61308,
    "gzipped": 18372
  },
  "esm/react-final-form-components.js": {
    "bundled": 33301,
    "minified": 21197,
    "gzipped": 4588,
    "treeshaked": {
      "rollup": {
        "code": 17090,
        "import_statements": 635
      },
      "webpack": {
        "code": 19705
      }
    }
  },
  "umd/react-final-form-components.js": {
    "bundled": 306661,
    "minified": 112293,
    "gzipped": 33503
  },
  "umd/react-final-form-components.min.js": {
    "bundled": 143851,
    "minified": 63966,
    "gzipped": 18915
  }
}
